{"SU+7zLRCny+Yw+R63Ga4kQ==":"1.png","BK+RvfdxeENYdxqXSqN0xw==":"3.png","ZrZs+ZTl0cFoV/ooRCmY1Q==":"simon%20says-621x446.png","3aJb5Jv4gk+4sdWhX9touw==":"tinkercad-1-816x436.png","gdTlOT/f6V4u7bhamHUyRA==":"android%20app-816x378.png","rjBhiEyX5/MECe4NI+YxFg==":"133713169_3708759015877232_1991463110117653310_n-1256x1256.jpg","+kkWXgFFYjkepWTmrxnznQ==":"mp4-1256x775.png","ppCw1qvSCQJTEuGn2eC0nA==":"mp1-2-1256x877.png","BTncqSMr5nh4g42AAQ60rA==":"mp2-1-1058x968.png","h2O89/h+IlGbGY35VmnIYg==":"mp2-1-1218x844.png","Ac0usSjRW5QwIs+zbwit3w==":"mp2-2-1218x844.png","TpDfFBTqtYzpcmsWj43U0g==":"mp3-1256x637.png","thBTndGcE1PgffEZvhEIcA==":"mp3-1-1256x637.png","rsx9Uyz/0DpYz/7bRUFCNQ==":"mp4-1-1256x775.png","oA4h3t1TeL/e6QSlIIwwDg==":"mp4-1218x978.png","dLIYk19Rh0t57RBcmRVWHA==":"mp3-1218x844.png","gcZNP5KpeMpm9je2GZVPbg==":"mp4-1-1218x978.png","Mntvwn88CzJwUzSH4qmMig==":"mp3-1218x952.png","sCcc+AszqNgphr/DhRr2aQ==":"mp3-1-1218x844.png"}